endstone_test_plugin/__init__.py
endstone_test_plugin/test_plugin.py
endstone_test_plugin-0.1.0.dist-info/METADATA
endstone_test_plugin-0.1.0.dist-info/WHEEL
endstone_test_plugin-0.1.0.dist-info/entry_points.txt
endstone_test_plugin-0.1.0.dist-info/RECORD
