Metadata-Version: 2.4
Name: endstone-test-plugin
Version: 0.1.0
Summary: Example plugin for testing purposes
